pyhsd.cp39-win_amd64.pyd
pyhsd-1.1.1.dist-info/LICENSE.md
pyhsd-1.1.1.dist-info/METADATA
pyhsd-1.1.1.dist-info/WHEEL
pyhsd-1.1.1.dist-info/top_level.txt
pyhsd-1.1.1.dist-info/RECORD
