Metadata-Version: 2.1
Name: pyhsd
Version: 1.1.1
Summary: Humanized String Distance calculator
Home-page: https://bitbucket.org/pinetree-ai/algorithm-humanized-string-distance/src/master/
Author: Inventives.ai <https://inventives.ai>
Author-email: narendran.m@inventives.ai
License: CC-BY-NC 4.0
Platform: UNKNOWN
Classifier: Development Status :: 4 - Beta
Classifier: Programming Language :: Python :: 3 :: Only
Classifier: Topic :: Scientific/Engineering
Requires-Dist: setuptools
Requires-Dist: wheel
Requires-Dist: pybind11
